markdownmermaid/__init__.py
markdownmermaid/plugin.py
mkdocs_mermaid_plugin-0.1.1.dist-info/LICENSE
mkdocs_mermaid_plugin-0.1.1.dist-info/METADATA
mkdocs_mermaid_plugin-0.1.1.dist-info/WHEEL
mkdocs_mermaid_plugin-0.1.1.dist-info/entry_points.txt
mkdocs_mermaid_plugin-0.1.1.dist-info/top_level.txt
mkdocs_mermaid_plugin-0.1.1.dist-info/RECORD
